LICENSE
giant_plugins/__init__.py
giant_plugins/content_width_image/__init__.py
giant_plugins/content_width_image/cms_plugins.py
giant_plugins/content_width_image/migrations/0001_initial.py
giant_plugins/content_width_image/migrations/0002_contentwidthimage_credit.py
giant_plugins/content_width_image/migrations/0003_auto_20220621_1127.py
giant_plugins/content_width_image/migrations/0004_auto_20220915.py
giant_plugins/content_width_image/migrations/__init__.py
giant_plugins/content_width_image/models.py
giant_plugins/content_width_image/tests.py
giant_plugins/content_width_video/__init__.py
giant_plugins/content_width_video/cms_plugins.py
giant_plugins/content_width_video/migrations/0001_initial.py
giant_plugins/content_width_video/migrations/0002_contentwidthvideo_caption.py
giant_plugins/content_width_video/migrations/0003_auto_20220621_1127.py
giant_plugins/content_width_video/migrations/0004_alter_contentwidthvideo_image.py
giant_plugins/content_width_video/migrations/0004_alter_contentwidthvideo_youtube_url.py
giant_plugins/content_width_video/migrations/0005_remove_contentwidthvideo_alt_title.py
giant_plugins/content_width_video/migrations/0006_merge_20220729_0931.py
giant_plugins/content_width_video/migrations/0007_contentwidthvideo_anchor_id.py
giant_plugins/content_width_video/migrations/__init__.py
giant_plugins/content_width_video/models.py
giant_plugins/content_width_video/tests.py
giant_plugins/donate/__init__.py
giant_plugins/donate/cms_plugins.py
giant_plugins/donate/migrations/0001_initial.py
giant_plugins/donate/migrations/0002_donate_anchor_id.py
giant_plugins/donate/migrations/__init__.py
giant_plugins/donate/models.py
giant_plugins/donate/tests.py
giant_plugins/featured_cta/__init__.py
giant_plugins/featured_cta/cms_plugins.py
giant_plugins/featured_cta/migrations/0001_initial.py
giant_plugins/featured_cta/migrations/0002_featuredcta_new_tab.py
giant_plugins/featured_cta/migrations/__init__.py
giant_plugins/featured_cta/models.py
giant_plugins-1.0.18.dist-info/LICENSE
giant_plugins-1.0.18.dist-info/METADATA
giant_plugins-1.0.18.dist-info/WHEEL
giant_plugins-1.0.18.dist-info/RECORD
