Metadata-Version: 2.1
Name: giant-plugins
Version: 1.0.18
Summary: Adds a generic list of plugins for use within projects
Home-page: https://github.com/giantmade/giant-plugins
License: MIT
Keywords: plugins,app
Author: Will-Hoey
Author-email: will.hoey@giantdigital.co.uk
Requires-Python: >=3.9,<4.0
Classifier: Environment :: Console
Classifier: License :: OSI Approved :: MIT License
Classifier: Operating System :: OS Independent
Classifier: Programming Language :: Python :: 3
Classifier: Programming Language :: Python :: 3.9
Classifier: Programming Language :: Python :: 3.10
Classifier: Programming Language :: Python :: 3.11
Classifier: Topic :: Software Development :: Documentation
Classifier: Topic :: Software Development :: Libraries :: Python Modules
Requires-Dist: django-filer
Requires-Dist: giant-mixins
Requires-Dist: requests
Project-URL: Repository, https://github.com/giantmade/giant-plugins
